<?xml version="1.0" encoding="utf-8"?><PARAMS><PARAM ID="1644373972" OBJECTID="174909173" CHANGEID="689623301" CHANGEIDEND="0" TYPEID="1" VALUE="1700" UPDATEDATE="2025-09-29" STARTDATE="2025-09-29" ENDDATE="2079-06-06" /><PARAM ID="1644373973" OBJECTID="174909173" CHANGEID="689623301" CHANGEIDEND="0" TYPEID="2" VALUE="1700" UPDATEDATE="2025-09-29" STARTDATE="2025-09-29" ENDDATE="2079-06-06" /><PARAM ID="1644373974" OBJECTID="174909173" CHANGEID="689623301" CHANGEIDEND="0" TYPEID="6" VALUE="93222551000" UPDATEDATE="2025-09-29" STARTDATE="2025-09-29" ENDDATE="2079-06-06" /><PARAM ID="1644373975" OBJECTID="174909173" CHANGEID="689623301" CHANGEIDEND="0" TYPEID="7" VALUE="93622151051" UPDATEDATE="2025-09-29" STARTDATE="2025-09-29" ENDDATE="2079-06-06" /><PARAM ID="1644373976" OBJECTID="174909173" CHANGEID="689623301" CHANGEIDEND="0" TYPEID="8" VALUE="17:05:1702001:5171" UPDATEDATE="2025-09-29" STARTDATE="2025-09-29" ENDDATE="2079-06-06" /><PARAM ID="1644373977" OBJECTID="174909173" CHANGEID="689623301" CHANGEIDEND="0" TYPEID="15" VALUE="20" UPDATEDATE="2025-09-29" STARTDATE="2025-09-29" ENDDATE="2079-06-06" /><PARAM ID="1644373978" OBJECTID="174909173" CHANGEID="689623301" CHANGEIDEND="0" TYPEID="13" VALUE="936221510510000017610020000000000" UPDATEDATE="2025-09-29" STARTDATE="2025-09-29" ENDDATE="2079-06-06" /><PARAM ID="1644373979" OBJECTID="174909173" CHANGEID="689623301" CHANGEIDEND="0" TYPEID="21" VALUE="93622151" UPDATEDATE="2025-09-29" STARTDATE="2025-09-29" ENDDATE="2079-06-06" /><PARAM ID="1644382635" OBJECTID="174910157" CHANGEID="689624696" CHANGEIDEND="0" TYPEID="1" VALUE="1700" UPDATEDATE="2025-09-29" STARTDATE="2025-09-29" ENDDATE="2079-06-06" /><PARAM ID="1644382636" OBJECTID="174910157" CHANGEID="689624696" CHANGEIDEND="0" TYPEID="2" VALUE="1700" UPDATEDATE="2025-09-29" STARTDATE="2025-09-29" ENDDATE="2079-06-06" /><PARAM ID="1644382637" OBJECTID="174910157" CHANGEID="689624696" CHANGEIDEND="0" TYPEID="6" VALUE="93222845001" UPDATEDATE="2025-09-29" STARTDATE="2025-09-29" ENDDATE="2079-06-06" /><PARAM ID="1644382638" OBJECTID="174910157" CHANGEID="689624696" CHANGEIDEND="0" TYPEID="7" VALUE="93622445101" UPDATEDATE="2025-09-29" STARTDATE="2025-09-29" ENDDATE="2079-06-06" /><PARAM ID="1644382639" OBJECTID="174910157" CHANGEID="689624696" CHANGEIDEND="0" TYPEID="15" VALUE="1" UPDATEDATE="2025-09-29" STARTDATE="2025-09-29" ENDDATE="2079-06-06" /><PARAM ID="1644382640" OBJECTID="174910157" CHANGEID="689624696" CHANGEIDEND="0" TYPEID="13" VALUE="936224451010000000210001000000000" UPDATEDATE="2025-09-29" STARTDATE="2025-09-29" ENDDATE="2079-06-06" /><PARAM ID="1644382641" OBJECTID="174910157" CHANGEID="689624696" CHANGEIDEND="0" TYPEID="21" VALUE="93622445" UPDATEDATE="2025-09-29" STARTDATE="2025-09-29" ENDDATE="2079-06-06" /><PARAM ID="1644382649" OBJECTID="174910159" CHANGEID="689624698" CHANGEIDEND="0" TYPEID="1" VALUE="1700" UPDATEDATE="2025-09-29" STARTDATE="2025-09-29" ENDDATE="2079-06-06" /><PARAM ID="1644382650" OBJECTID="174910159" CHANGEID="689624698" CHANGEIDEND="0" TYPEID="2" VALUE="1700" UPDATEDATE="2025-09-29" STARTDATE="2025-09-29" ENDDATE="2079-06-06" /><PARAM ID="1644382651" OBJECTID="174910159" CHANGEID="689624698" CHANGEIDEND="0" TYPEID="6" VALUE="93222845001" UPDATEDATE="2025-09-29" STARTDATE="2025-09-29" ENDDATE="2079-06-06" /><PARAM ID="1644382652" OBJECTID="174910159" CHANGEID="689624698" CHANGEIDEND="0" TYPEID="7" VALUE="93622445101" UPDATEDATE="2025-09-29" STARTDATE="2025-09-29" ENDDATE="2079-06-06" /><PARAM ID="1644382653" OBJECTID="174910159" CHANGEID="689624698" CHANGEIDEND="0" TYPEID="15" VALUE="3" UPDATEDATE="2025-09-29" STARTDATE="2025-09-29" ENDDATE="2079-06-06" /><PARAM ID="1644382642" OBJECTID="174910158" CHANGEID="689624697" CHANGEIDEND="0" TYPEID="1" VALUE="1700" UPDATEDATE="2025-09-29" STARTDATE="2025-09-29" ENDDATE="2079-06-06" /><PARAM ID="1644382643" OBJECTID="174910158" CHANGEID="689624697" CHANGEIDEND="0" TYPEID="2" VALUE="1700" UPDATEDATE="2025-09-29" STARTDATE="2025-09-29" ENDDATE="2079-06-06" /><PARAM ID="1644382644" OBJECTID="174910158" CHANGEID="689624697" CHANGEIDEND="0" TYPEID="6" VALUE="93222845001" UPDATEDATE="2025-09-29" STARTDATE="2025-09-29" ENDDATE="2079-06-06" /><PARAM ID="1644382645" OBJECTID="174910158" CHANGEID="689624697" CHANGEIDEND="0" TYPEID="7" VALUE="93622445101" UPDATEDATE="2025-09-29" STARTDATE="2025-09-29" ENDDATE="2079-06-06" /><PARAM ID="1644382646" OBJECTID="174910158" CHANGEID="689624697" CHANGEIDEND="0" TYPEID="15" VALUE="2" UPDATEDATE="2025-09-29" STARTDATE="2025-09-29" ENDDATE="2079-06-06" /><PARAM ID="1644382647" OBJECTID="174910158" CHANGEID="689624697" CHANGEIDEND="0" TYPEID="13" VALUE="936224451010000000210002000000000" UPDATEDATE="2025-09-29" STARTDATE="2025-09-29" ENDDATE="2079-06-06" /><PARAM ID="1644382648" OBJECTID="174910158" CHANGEID="689624697" CHANGEIDEND="0" TYPEID="21" VALUE="93622445" UPDATEDATE="2025-09-29" STARTDATE="2025-09-29" ENDDATE="2079-06-06" /><PARAM ID="1644382654" OBJECTID="174910159" CHANGEID="689624698" CHANGEIDEND="0" TYPEID="13" VALUE="936224451010000000210003000000000" UPDATEDATE="2025-09-29" STARTDATE="2025-09-29" ENDDATE="2079-06-06" /><PARAM ID="1644382655" OBJECTID="174910159" CHANGEID="689624698" CHANGEIDEND="0" TYPEID="21" VALUE="93622445" UPDATEDATE="2025-09-29" STARTDATE="2025-09-29" ENDDATE="2079-06-06" /><PARAM ID="1644386159" OBJECTID="174910793" CHANGEID="689625903" CHANGEIDEND="0" TYPEID="1" VALUE="1700" UPDATEDATE="2025-09-29" STARTDATE="2025-09-29" ENDDATE="2079-06-06" /><PARAM ID="1644386160" OBJECTID="174910793" CHANGEID="689625903" CHANGEIDEND="0" TYPEID="2" VALUE="1700" UPDATEDATE="2025-09-29" STARTDATE="2025-09-29" ENDDATE="2079-06-06" /><PARAM ID="1644386161" OBJECTID="174910793" CHANGEID="689625903" CHANGEIDEND="0" TYPEID="6" VALUE="93235825001" UPDATEDATE="2025-09-29" STARTDATE="2025-09-29" ENDDATE="2079-06-06" /><PARAM ID="1644386162" OBJECTID="174910793" CHANGEID="689625903" CHANGEIDEND="0" TYPEID="7" VALUE="93635425101" UPDATEDATE="2025-09-29" STARTDATE="2025-09-29" ENDDATE="2079-06-06" /><PARAM ID="1644386163" OBJECTID="174910793" CHANGEID="689625903" CHANGEIDEND="0" TYPEID="8" VALUE="17:08:0802001:439" UPDATEDATE="2025-09-29" STARTDATE="2025-09-29" ENDDATE="2079-06-06" /><PARAM ID="1644386164" OBJECTID="174910793" CHANGEID="689625903" CHANGEIDEND="0" TYPEID="15" VALUE="4" UPDATEDATE="2025-09-29" STARTDATE="2025-09-29" ENDDATE="2079-06-06" /><PARAM ID="1644386165" OBJECTID="174910793" CHANGEID="689625903" CHANGEIDEND="0" TYPEID="13" VALUE="936354251010000004210004000000000" UPDATEDATE="2025-09-29" STARTDATE="2025-09-29" ENDDATE="2079-06-06" /><PARAM ID="1644386166" OBJECTID="174910793" CHANGEID="689625903" CHANGEIDEND="0" TYPEID="21" VALUE="93635425" UPDATEDATE="2025-09-29" STARTDATE="2025-09-29" ENDDATE="2079-06-06" /><PARAM ID="1644386167" OBJECTID="174910794" CHANGEID="689625904" CHANGEIDEND="0" TYPEID="1" VALUE="1700" UPDATEDATE="2025-09-29" STARTDATE="2025-09-29" ENDDATE="2079-06-06" /><PARAM ID="1644386168" OBJECTID="174910794" CHANGEID="689625904" CHANGEIDEND="0" TYPEID="2" VALUE="1700" UPDATEDATE="2025-09-29" STARTDATE="2025-09-29" ENDDATE="2079-06-06" /><PARAM ID="1644386169" OBJECTID="174910794" CHANGEID="689625904" CHANGEIDEND="0" TYPEID="6" VALUE="93235825001" UPDATEDATE="2025-09-29" STARTDATE="2025-09-29" ENDDATE="2079-06-06" /><PARAM ID="1644386170" OBJECTID="174910794" CHANGEID="689625904" CHANGEIDEND="0" TYPEID="7" VALUE="93635425101" UPDATEDATE="2025-09-29" STARTDATE="2025-09-29" ENDDATE="2079-06-06" /><PARAM ID="1644386171" OBJECTID="174910794" CHANGEID="689625904" CHANGEIDEND="0" TYPEID="8" VALUE="17:08:0802001:438" UPDATEDATE="2025-09-29" STARTDATE="2025-09-29" ENDDATE="2079-06-06" /><PARAM ID="1644386172" OBJECTID="174910794" CHANGEID="689625904" CHANGEIDEND="0" TYPEID="15" VALUE="5" UPDATEDATE="2025-09-29" STARTDATE="2025-09-29" ENDDATE="2079-06-06" /><PARAM ID="1644386173" OBJECTID="174910794" CHANGEID="689625904" CHANGEIDEND="0" TYPEID="13" VALUE="936354251010000004210005000000000" UPDATEDATE="2025-09-29" STARTDATE="2025-09-29" ENDDATE="2079-06-06" /><PARAM ID="1644386174" OBJECTID="174910794" CHANGEID="689625904" CHANGEIDEND="0" TYPEID="21" VALUE="93635425" UPDATEDATE="2025-09-29" STARTDATE="2025-09-29" ENDDATE="2079-06-06" /><PARAM ID="1644387004" OBJECTID="174910936" CHANGEID="689626550" CHANGEIDEND="0" TYPEID="1" VALUE="1700" UPDATEDATE="2025-09-29" STARTDATE="2025-09-29" ENDDATE="2079-06-06" /><PARAM ID="1644387005" OBJECTID="174910936" CHANGEID="689626550" CHANGEIDEND="0" TYPEID="2" VALUE="1700" UPDATEDATE="2025-09-29" STARTDATE="2025-09-29" ENDDATE="2079-06-06" /><PARAM ID="1644387006" OBJECTID="174910936" CHANGEID="689626550" CHANGEIDEND="0" TYPEID="6" VALUE="93222845001" UPDATEDATE="2025-09-29" STARTDATE="2025-09-29" ENDDATE="2079-06-06" /><PARAM ID="1644387007" OBJECTID="174910936" CHANGEID="689626550" CHANGEIDEND="0" TYPEID="7" VALUE="93622445101" UPDATEDATE="2025-09-29" STARTDATE="2025-09-29" ENDDATE="2079-06-06" /><PARAM ID="1644387008" OBJECTID="174910936" CHANGEID="689626550" CHANGEIDEND="0" TYPEID="15" VALUE="22" UPDATEDATE="2025-09-29" STARTDATE="2025-09-29" ENDDATE="2079-06-06" /><PARAM ID="1644387009" OBJECTID="174910936" CHANGEID="689626550" CHANGEIDEND="0" TYPEID="13" VALUE="936224451010000001210022000000000" UPDATEDATE="2025-09-29" STARTDATE="2025-09-29" ENDDATE="2079-06-06" /><PARAM ID="1644387010" OBJECTID="174910936" CHANGEID="689626550" CHANGEIDEND="0" TYPEID="21" VALUE="93622445" UPDATEDATE="2025-09-29" STARTDATE="2025-09-29" ENDDATE="2079-06-06" /><PARAM ID="1644387018" OBJECTID="174910938" CHANGEID="689626552" CHANGEIDEND="0" TYPEID="1" VALUE="1700" UPDATEDATE="2025-09-29" STARTDATE="2025-09-29" ENDDATE="2079-06-06" /><PARAM ID="1644387019" OBJECTID="174910938" CHANGEID="689626552" CHANGEIDEND="0" TYPEID="2" VALUE="1700" UPDATEDATE="2025-09-29" STARTDATE="2025-09-29" ENDDATE="2079-06-06" /><PARAM ID="1644387020" OBJECTID="174910938" CHANGEID="689626552" CHANGEIDEND="0" TYPEID="6" VALUE="93222845001" UPDATEDATE="2025-09-29" STARTDATE="2025-09-29" ENDDATE="2079-06-06" /><PARAM ID="1644387021" OBJECTID="174910938" CHANGEID="689626552" CHANGEIDEND="0" TYPEID="7" VALUE="93622445101" UPDATEDATE="2025-09-29" STARTDATE="2025-09-29" ENDDATE="2079-06-06" /><PARAM ID="1644387022" OBJECTID="174910938" CHANGEID="689626552" CHANGEIDEND="0" TYPEID="15" VALUE="3" UPDATEDATE="2025-09-29" STARTDATE="2025-09-29" ENDDATE="2079-06-06" /><PARAM ID="1644387023" OBJECTID="174910938" CHANGEID="689626552" CHANGEIDEND="0" TYPEID="13" VALUE="936224451010000001610003000000000" UPDATEDATE="2025-09-29" STARTDATE="2025-09-29" ENDDATE="2079-06-06" /><PARAM ID="1644387024" OBJECTID="174910938" CHANGEID="689626552" CHANGEIDEND="0" TYPEID="21" VALUE="93622445" UPDATEDATE="2025-09-29" STARTDATE="2025-09-29" ENDDATE="2079-06-06" /><PARAM ID="1644386997" OBJECTID="174910935" CHANGEID="689626549" CHANGEIDEND="0" TYPEID="1" VALUE="1700" UPDATEDATE="2025-09-29" STARTDATE="2025-09-29" ENDDATE="2079-06-06" /><PARAM ID="1644386998" OBJECTID="174910935" CHANGEID="689626549" CHANGEIDEND="0" TYPEID="2" VALUE="1700" UPDATEDATE="2025-09-29" STARTDATE="2025-09-29" ENDDATE="2079-06-06" /><PARAM ID="1644386999" OBJECTID="174910935" CHANGEID="689626549" CHANGEIDEND="0" TYPEID="6" VALUE="93222845001" UPDATEDATE="2025-09-29" STARTDATE="2025-09-29" ENDDATE="2079-06-06" /><PARAM ID="1644387000" OBJECTID="174910935" CHANGEID="689626549" CHANGEIDEND="0" TYPEID="7" VALUE="93622445101" UPDATEDATE="2025-09-29" STARTDATE="2025-09-29" ENDDATE="2079-06-06" /><PARAM ID="1644387001" OBJECTID="174910935" CHANGEID="689626549" CHANGEIDEND="0" TYPEID="15" VALUE="1" UPDATEDATE="2025-09-29" STARTDATE="2025-09-29" ENDDATE="2079-06-06" /><PARAM ID="1644387002" OBJECTID="174910935" CHANGEID="689626549" CHANGEIDEND="0" TYPEID="13" VALUE="936224451010000001610001000000000" UPDATEDATE="2025-09-29" STARTDATE="2025-09-29" ENDDATE="2079-06-06" /><PARAM ID="1644387003" OBJECTID="174910935" CHANGEID="689626549" CHANGEIDEND="0" TYPEID="21" VALUE="93622445" UPDATEDATE="2025-09-29" STARTDATE="2025-09-29" ENDDATE="2079-06-06" /><PARAM ID="1644387011" OBJECTID="174910937" CHANGEID="689626551" CHANGEIDEND="0" TYPEID="1" VALUE="1700" UPDATEDATE="2025-09-29" STARTDATE="2025-09-29" ENDDATE="2079-06-06" /><PARAM ID="1644387012" OBJECTID="174910937" CHANGEID="689626551" CHANGEIDEND="0" TYPEID="2" VALUE="1700" UPDATEDATE="2025-09-29" STARTDATE="2025-09-29" ENDDATE="2079-06-06" /><PARAM ID="1644387013" OBJECTID="174910937" CHANGEID="689626551" CHANGEIDEND="0" TYPEID="6" VALUE="93222845001" UPDATEDATE="2025-09-29" STARTDATE="2025-09-29" ENDDATE="2079-06-06" /><PARAM ID="1644387014" OBJECTID="174910937" CHANGEID="689626551" CHANGEIDEND="0" TYPEID="7" VALUE="93622445101" UPDATEDATE="2025-09-29" STARTDATE="2025-09-29" ENDDATE="2079-06-06" /><PARAM ID="1644387015" OBJECTID="174910937" CHANGEID="689626551" CHANGEIDEND="0" TYPEID="15" VALUE="2" UPDATEDATE="2025-09-29" STARTDATE="2025-09-29" ENDDATE="2079-06-06" /><PARAM ID="1644387016" OBJECTID="174910937" CHANGEID="689626551" CHANGEIDEND="0" TYPEID="13" VALUE="936224451010000001610002000000000" UPDATEDATE="2025-09-29" STARTDATE="2025-09-29" ENDDATE="2079-06-06" /><PARAM ID="1644387017" OBJECTID="174910937" CHANGEID="689626551" CHANGEIDEND="0" TYPEID="21" VALUE="93622445" UPDATEDATE="2025-09-29" STARTDATE="2025-09-29" ENDDATE="2079-06-06" /><PARAM ID="1644404255" OBJECTID="174912915" CHANGEID="689631783" CHANGEIDEND="0" TYPEID="1" VALUE="1700" UPDATEDATE="2025-09-29" STARTDATE="2025-09-29" ENDDATE="2079-06-06" /><PARAM ID="1644404256" OBJECTID="174912915" CHANGEID="689631783" CHANGEIDEND="0" TYPEID="2" VALUE="1700" UPDATEDATE="2025-09-29" STARTDATE="2025-09-29" ENDDATE="2079-06-06" /><PARAM ID="1644404257" OBJECTID="174912915" CHANGEID="689631783" CHANGEIDEND="0" TYPEID="6" VALUE="93215501000" UPDATEDATE="2025-09-29" STARTDATE="2025-09-29" ENDDATE="2079-06-06" /><PARAM ID="1644404258" OBJECTID="174912915" CHANGEID="689631783" CHANGEIDEND="0" TYPEID="7" VALUE="93615101001" UPDATEDATE="2025-09-29" STARTDATE="2025-09-29" ENDDATE="2079-06-06" /><PARAM ID="1644404259" OBJECTID="174912915" CHANGEID="689631783" CHANGEIDEND="0" TYPEID="8" VALUE="17:03:0601148:163" UPDATEDATE="2025-09-29" STARTDATE="2025-09-29" ENDDATE="2079-06-06" /><PARAM ID="1644404260" OBJECTID="174912915" CHANGEID="689631783" CHANGEIDEND="0" TYPEID="15" VALUE="3" UPDATEDATE="2025-09-29" STARTDATE="2025-09-29" ENDDATE="2079-06-06" /><PARAM ID="1644404261" OBJECTID="174912915" CHANGEID="689631783" CHANGEIDEND="0" TYPEID="13" VALUE="936151010010000002410003000000000" UPDATEDATE="2025-09-29" STARTDATE="2025-09-29" ENDDATE="2079-06-06" /><PARAM ID="1644404262" OBJECTID="174912915" CHANGEID="689631783" CHANGEIDEND="0" TYPEID="21" VALUE="93615101" UPDATEDATE="2025-09-29" STARTDATE="2025-09-29" ENDDATE="2079-06-06" /><PARAM ID="1644529769" OBJECTID="174930535" CHANGEID="689669827" CHANGEIDEND="0" TYPEID="1" VALUE="1700" UPDATEDATE="2025-09-29" STARTDATE="2025-09-29" ENDDATE="2079-06-06" /><PARAM ID="1644529770" OBJECTID="174930535" CHANGEID="689669827" CHANGEIDEND="0" TYPEID="2" VALUE="1700" UPDATEDATE="2025-09-29" STARTDATE="2025-09-29" ENDDATE="2079-06-06" /><PARAM ID="1644529771" OBJECTID="174930535" CHANGEID="689669827" CHANGEIDEND="0" TYPEID="6" VALUE="93401000000" UPDATEDATE="2025-09-29" STARTDATE="2025-09-29" ENDDATE="2079-06-06" /><PARAM ID="1644529772" OBJECTID="174930535" CHANGEID="689669827" CHANGEIDEND="0" TYPEID="7" VALUE="93701000001" UPDATEDATE="2025-09-29" STARTDATE="2025-09-29" ENDDATE="2079-06-06" /><PARAM ID="1644529773" OBJECTID="174930535" CHANGEID="689669827" CHANGEIDEND="0" TYPEID="8" VALUE="17:18:0104003:725" UPDATEDATE="2025-09-29" STARTDATE="2025-09-29" ENDDATE="2079-06-06" /><PARAM ID="1644529774" OBJECTID="174930535" CHANGEID="689669827" CHANGEIDEND="0" TYPEID="15" VALUE="66" UPDATEDATE="2025-09-29" STARTDATE="2025-09-29" ENDDATE="2079-06-06" /><PARAM ID="1644529775" OBJECTID="174930535" CHANGEID="689669827" CHANGEIDEND="0" TYPEID="13" VALUE="937010000010744074610066000000000" UPDATEDATE="2025-09-29" STARTDATE="2025-09-29" ENDDATE="2079-06-06" /><PARAM ID="1644529776" OBJECTID="174930535" CHANGEID="689669827" CHANGEIDEND="0" TYPEID="21" VALUE="93701000" UPDATEDATE="2025-09-29" STARTDATE="2025-09-29" ENDDATE="2079-06-06" /><PARAM ID="1644643802" OBJECTID="174946174" CHANGEID="689703449" CHANGEIDEND="0" TYPEID="1" VALUE="1700" UPDATEDATE="2025-09-30" STARTDATE="2025-09-30" ENDDATE="2079-06-06" /><PARAM ID="1644643803" OBJECTID="174946174" CHANGEID="689703449" CHANGEIDEND="0" TYPEID="2" VALUE="1700" UPDATEDATE="2025-09-30" STARTDATE="2025-09-30" ENDDATE="2079-06-06" /><PARAM ID="1644643804" OBJECTID="174946174" CHANGEID="689703449" CHANGEIDEND="0" TYPEID="6" VALUE="93256840001" UPDATEDATE="2025-09-30" STARTDATE="2025-09-30" ENDDATE="2079-06-06" /><PARAM ID="1644643805" OBJECTID="174946174" CHANGEID="689703449" CHANGEIDEND="0" TYPEID="7" VALUE="93656440101" UPDATEDATE="2025-09-30" STARTDATE="2025-09-30" ENDDATE="2079-06-06" /><PARAM ID="1644643806" OBJECTID="174946174" CHANGEID="689703449" CHANGEIDEND="0" TYPEID="15" VALUE="56" UPDATEDATE="2025-09-30" STARTDATE="2025-09-30" ENDDATE="2079-06-06" /><PARAM ID="1644643807" OBJECTID="174946174" CHANGEID="689703449" CHANGEIDEND="0" TYPEID="13" VALUE="936564401010000000110056000000000" UPDATEDATE="2025-09-30" STARTDATE="2025-09-30" ENDDATE="2079-06-06" /><PARAM ID="1644643808" OBJECTID="174946174" CHANGEID="689703449" CHANGEIDEND="0" TYPEID="21" VALUE="93656440" UPDATEDATE="2025-09-30" STARTDATE="2025-09-30" ENDDATE="2079-06-06" /><PARAM ID="1644648108" OBJECTID="174946883" CHANGEID="689704455" CHANGEIDEND="0" TYPEID="1" VALUE="1700" UPDATEDATE="2025-09-30" STARTDATE="2025-09-30" ENDDATE="2079-06-06" /><PARAM ID="1644648109" OBJECTID="174946883" CHANGEID="689704455" CHANGEIDEND="0" TYPEID="2" VALUE="1700" UPDATEDATE="2025-09-30" STARTDATE="2025-09-30" ENDDATE="2079-06-06" /><PARAM ID="1644648110" OBJECTID="174946883" CHANGEID="689704455" CHANGEIDEND="0" TYPEID="6" VALUE="93245833001" UPDATEDATE="2025-09-30" STARTDATE="2025-09-30" ENDDATE="2079-06-06" /><PARAM ID="1644648111" OBJECTID="174946883" CHANGEID="689704455" CHANGEIDEND="0" TYPEID="7" VALUE="93645433101" UPDATEDATE="2025-09-30" STARTDATE="2025-09-30" ENDDATE="2079-06-06" /><PARAM ID="1644648112" OBJECTID="174946883" CHANGEID="689704455" CHANGEIDEND="0" TYPEID="8" VALUE="17:12:0601043:1014" UPDATEDATE="2025-09-30" STARTDATE="2025-09-30" ENDDATE="2079-06-06" /><PARAM ID="1644648113" OBJECTID="174946883" CHANGEID="689704455" CHANGEIDEND="0" TYPEID="15" VALUE="2" UPDATEDATE="2025-09-30" STARTDATE="2025-09-30" ENDDATE="2079-06-06" /><PARAM ID="1644648114" OBJECTID="174946883" CHANGEID="689704455" CHANGEIDEND="0" TYPEID="13" VALUE="936454331010000001510002000000000" UPDATEDATE="2025-09-30" STARTDATE="2025-09-30" ENDDATE="2079-06-06" /><PARAM ID="1644648115" OBJECTID="174946883" CHANGEID="689704455" CHANGEIDEND="0" TYPEID="21" VALUE="93645433" UPDATEDATE="2025-09-30" STARTDATE="2025-09-30" ENDDATE="2079-06-06" /><PARAM ID="1644651114" OBJECTID="174947245" CHANGEID="689705049" CHANGEIDEND="0" TYPEID="1" VALUE="1700" UPDATEDATE="2025-09-30" STARTDATE="2025-09-30" ENDDATE="2079-06-06" /><PARAM ID="1644651115" OBJECTID="174947245" CHANGEID="689705049" CHANGEIDEND="0" TYPEID="2" VALUE="1700" UPDATEDATE="2025-09-30" STARTDATE="2025-09-30" ENDDATE="2079-06-06" /><PARAM ID="1644651116" OBJECTID="174947245" CHANGEID="689705049" CHANGEIDEND="0" TYPEID="6" VALUE="93215838001" UPDATEDATE="2025-09-30" STARTDATE="2025-09-30" ENDDATE="2079-06-06" /><PARAM ID="1644651117" OBJECTID="174947245" CHANGEID="689705049" CHANGEIDEND="0" TYPEID="7" VALUE="93615438101" UPDATEDATE="2025-09-30" STARTDATE="2025-09-30" ENDDATE="2079-06-06" /><PARAM ID="1644651118" OBJECTID="174947245" CHANGEID="689705049" CHANGEIDEND="0" TYPEID="8" VALUE="17:03:1001019:28" UPDATEDATE="2025-09-30" STARTDATE="2025-09-30" ENDDATE="2079-06-06" /><PARAM ID="1644651119" OBJECTID="174947245" CHANGEID="689705049" CHANGEIDEND="0" TYPEID="15" VALUE="3" UPDATEDATE="2025-09-30" STARTDATE="2025-09-30" ENDDATE="2079-06-06" /><PARAM ID="1644651120" OBJECTID="174947245" CHANGEID="689705049" CHANGEIDEND="0" TYPEID="13" VALUE="936154381010000000610003000000000" UPDATEDATE="2025-09-30" STARTDATE="2025-09-30" ENDDATE="2079-06-06" /><PARAM ID="1644651121" OBJECTID="174947245" CHANGEID="689705049" CHANGEIDEND="0" TYPEID="21" VALUE="93615438" UPDATEDATE="2025-09-30" STARTDATE="2025-09-30" ENDDATE="2079-06-06" /><PARAM ID="1644700681" OBJECTID="174952616" CHANGEID="689717706" CHANGEIDEND="0" TYPEID="1" VALUE="1700" UPDATEDATE="2025-09-30" STARTDATE="2025-09-30" ENDDATE="2079-06-06" /><PARAM ID="1644700682" OBJECTID="174952616" CHANGEID="689717706" CHANGEIDEND="0" TYPEID="2" VALUE="1700" UPDATEDATE="2025-09-30" STARTDATE="2025-09-30" ENDDATE="2079-06-06" /><PARAM ID="1644700683" OBJECTID="174952616" CHANGEID="689717706" CHANGEIDEND="0" TYPEID="6" VALUE="93215501000" UPDATEDATE="2025-09-30" STARTDATE="2025-09-30" ENDDATE="2079-06-06" /><PARAM ID="1644700684" OBJECTID="174952616" CHANGEID="689717706" CHANGEIDEND="0" TYPEID="7" VALUE="93615101001" UPDATEDATE="2025-09-30" STARTDATE="2025-09-30" ENDDATE="2079-06-06" /><PARAM ID="1644700685" OBJECTID="174952616" CHANGEID="689717706" CHANGEIDEND="0" TYPEID="8" VALUE="17:03:1602003:200" UPDATEDATE="2025-09-30" STARTDATE="2025-09-30" ENDDATE="2079-06-06" /><PARAM ID="1644700686" OBJECTID="174952616" CHANGEID="689717706" CHANGEIDEND="0" TYPEID="15" VALUE="1" UPDATEDATE="2025-09-30" STARTDATE="2025-09-30" ENDDATE="2079-06-06" /><PARAM ID="1644700687" OBJECTID="174952616" CHANGEID="689717706" CHANGEIDEND="0" TYPEID="13" VALUE="936151010010000006510001000000000" UPDATEDATE="2025-09-30" STARTDATE="2025-09-30" ENDDATE="2079-06-06" /><PARAM ID="1644700688" OBJECTID="174952616" CHANGEID="689717706" CHANGEIDEND="0" TYPEID="21" VALUE="93615101" UPDATEDATE="2025-09-30" STARTDATE="2025-09-30" ENDDATE="2079-06-06" /><PARAM ID="1644700689" OBJECTID="174952617" CHANGEID="689717707" CHANGEIDEND="0" TYPEID="1" VALUE="1700" UPDATEDATE="2025-09-30" STARTDATE="2025-09-30" ENDDATE="2079-06-06" /><PARAM ID="1644700690" OBJECTID="174952617" CHANGEID="689717707" CHANGEIDEND="0" TYPEID="2" VALUE="1700" UPDATEDATE="2025-09-30" STARTDATE="2025-09-30" ENDDATE="2079-06-06" /><PARAM ID="1644700691" OBJECTID="174952617" CHANGEID="689717707" CHANGEIDEND="0" TYPEID="6" VALUE="93215501000" UPDATEDATE="2025-09-30" STARTDATE="2025-09-30" ENDDATE="2079-06-06" /><PARAM ID="1644700692" OBJECTID="174952617" CHANGEID="689717707" CHANGEIDEND="0" TYPEID="7" VALUE="93615101001" UPDATEDATE="2025-09-30" STARTDATE="2025-09-30" ENDDATE="2079-06-06" /><PARAM ID="1644700693" OBJECTID="174952617" CHANGEID="689717707" CHANGEIDEND="0" TYPEID="8" VALUE="17:03:1602003:201" UPDATEDATE="2025-09-30" STARTDATE="2025-09-30" ENDDATE="2079-06-06" /><PARAM ID="1644700694" OBJECTID="174952617" CHANGEID="689717707" CHANGEIDEND="0" TYPEID="15" VALUE="2" UPDATEDATE="2025-09-30" STARTDATE="2025-09-30" ENDDATE="2079-06-06" /><PARAM ID="1644700695" OBJECTID="174952617" CHANGEID="689717707" CHANGEIDEND="0" TYPEID="13" VALUE="936151010010000006510002000000000" UPDATEDATE="2025-09-30" STARTDATE="2025-09-30" ENDDATE="2079-06-06" /><PARAM ID="1644700696" OBJECTID="174952617" CHANGEID="689717707" CHANGEIDEND="0" TYPEID="21" VALUE="93615101" UPDATEDATE="2025-09-30" STARTDATE="2025-09-30" ENDDATE="2079-06-06" /><PARAM ID="1644775218" OBJECTID="105100632" CHANGEID="689739065" CHANGEIDEND="0" TYPEID="13" VALUE="937010000010533056210078000000010" UPDATEDATE="2025-09-30" STARTDATE="2025-09-30" ENDDATE="2079-06-06" /><PARAM ID="1644777437" OBJECTID="174962084" CHANGEID="689739946" CHANGEIDEND="0" TYPEID="1" VALUE="1700" UPDATEDATE="2025-09-30" STARTDATE="2025-09-30" ENDDATE="2079-06-06" /><PARAM ID="1644777438" OBJECTID="174962084" CHANGEID="689739946" CHANGEIDEND="0" TYPEID="2" VALUE="1700" UPDATEDATE="2025-09-30" STARTDATE="2025-09-30" ENDDATE="2079-06-06" /><PARAM ID="1644777439" OBJECTID="174962084" CHANGEID="689739946" CHANGEIDEND="0" TYPEID="6" VALUE="93222551000" UPDATEDATE="2025-09-30" STARTDATE="2025-09-30" ENDDATE="2079-06-06" /><PARAM ID="1644777440" OBJECTID="174962084" CHANGEID="689739946" CHANGEIDEND="0" TYPEID="7" VALUE="93622151051" UPDATEDATE="2025-09-30" STARTDATE="2025-09-30" ENDDATE="2079-06-06" /><PARAM ID="1644777441" OBJECTID="174962084" CHANGEID="689739946" CHANGEIDEND="0" TYPEID="8" VALUE="17:05:1702001:4955" UPDATEDATE="2025-09-30" STARTDATE="2025-09-30" ENDDATE="2079-06-06" /><PARAM ID="1644777442" OBJECTID="174962084" CHANGEID="689739946" CHANGEIDEND="0" TYPEID="15" VALUE="34" UPDATEDATE="2025-09-30" STARTDATE="2025-09-30" ENDDATE="2079-06-06" /><PARAM ID="1644777443" OBJECTID="174962084" CHANGEID="689739946" CHANGEIDEND="0" TYPEID="13" VALUE="936221510510000017410034000000000" UPDATEDATE="2025-09-30" STARTDATE="2025-09-30" ENDDATE="2079-06-06" /><PARAM ID="1644777444" OBJECTID="174962084" CHANGEID="689739946" CHANGEIDEND="0" TYPEID="21" VALUE="93622151" UPDATEDATE="2025-09-30" STARTDATE="2025-09-30" ENDDATE="2079-06-06" /><PARAM ID="1644780691" OBJECTID="84617848" CHANGEID="689740838" CHANGEIDEND="0" TYPEID="13" VALUE="937010000010744077210006000000010" UPDATEDATE="2025-09-30" STARTDATE="2025-09-30" ENDDATE="2079-06-06" /><PARAM ID="1644780986" OBJECTID="159088551" CHANGEID="689740916" CHANGEIDEND="0" TYPEID="13" VALUE="937010000010992000510051000000010" UPDATEDATE="2025-09-30" STARTDATE="2025-09-30" ENDDATE="2079-06-06" /><PARAM ID="1644781560" OBJECTID="86696080" CHANGEID="689741040" CHANGEIDEND="0" TYPEID="8" VALUE="17:08:1503003:959" UPDATEDATE="2025-09-30" STARTDATE="2025-09-30" ENDDATE="2079-06-06" /><PARAM ID="1644781561" OBJECTID="86696080" CHANGEID="689741040" CHANGEIDEND="0" TYPEID="13" VALUE="937010000010731073510014000000010" UPDATEDATE="2025-09-30" STARTDATE="2025-09-30" ENDDATE="2079-06-06" /><PARAM ID="1644782339" OBJECTID="174962607" CHANGEID="689741175" CHANGEIDEND="0" TYPEID="1" VALUE="1700" UPDATEDATE="2025-09-30" STARTDATE="2025-09-30" ENDDATE="2079-06-06" /><PARAM ID="1644782340" OBJECTID="174962607" CHANGEID="689741175" CHANGEIDEND="0" TYPEID="2" VALUE="1700" UPDATEDATE="2025-09-30" STARTDATE="2025-09-30" ENDDATE="2079-06-06" /><PARAM ID="1644782341" OBJECTID="174962607" CHANGEID="689741175" CHANGEIDEND="0" TYPEID="6" VALUE="93401000000" UPDATEDATE="2025-09-30" STARTDATE="2025-09-30" ENDDATE="2079-06-06" /><PARAM ID="1644782342" OBJECTID="174962607" CHANGEID="689741175" CHANGEIDEND="0" TYPEID="7" VALUE="93701000001" UPDATEDATE="2025-09-30" STARTDATE="2025-09-30" ENDDATE="2079-06-06" /><PARAM ID="1644782343" OBJECTID="174962607" CHANGEID="689741175" CHANGEIDEND="0" TYPEID="8" VALUE="17:18:0102001:6" UPDATEDATE="2025-09-30" STARTDATE="2025-09-30" ENDDATE="2079-06-06" /><PARAM ID="1644782344" OBJECTID="174962607" CHANGEID="689741175" CHANGEIDEND="0" TYPEID="15" VALUE="185" UPDATEDATE="2025-09-30" STARTDATE="2025-09-30" ENDDATE="2079-06-06" /><PARAM ID="1644782345" OBJECTID="174962607" CHANGEID="689741175" CHANGEIDEND="0" TYPEID="13" VALUE="937010000010000010710185000000000" UPDATEDATE="2025-09-30" STARTDATE="2025-09-30" ENDDATE="2079-06-06" /><PARAM ID="1644782346" OBJECTID="174962607" CHANGEID="689741175" CHANGEIDEND="0" TYPEID="21" VALUE="93701000" UPDATEDATE="2025-09-30" STARTDATE="2025-09-30" ENDDATE="2079-06-06" /><PARAM ID="1644782668" OBJECTID="174962647" CHANGEID="689741228" CHANGEIDEND="0" TYPEID="1" VALUE="1700" UPDATEDATE="2025-09-30" STARTDATE="2025-09-30" ENDDATE="2079-06-06" /><PARAM ID="1644782669" OBJECTID="174962647" CHANGEID="689741228" CHANGEIDEND="0" TYPEID="2" VALUE="1700" UPDATEDATE="2025-09-30" STARTDATE="2025-09-30" ENDDATE="2079-06-06" /><PARAM ID="1644782670" OBJECTID="174962647" CHANGEID="689741228" CHANGEIDEND="0" TYPEID="6" VALUE="93401000000" UPDATEDATE="2025-09-30" STARTDATE="2025-09-30" ENDDATE="2079-06-06" /><PARAM ID="1644782671" OBJECTID="174962647" CHANGEID="689741228" CHANGEIDEND="0" TYPEID="7" VALUE="93701000001" UPDATEDATE="2025-09-30" STARTDATE="2025-09-30" ENDDATE="2079-06-06" /><PARAM ID="1644782672" OBJECTID="174962647" CHANGEID="689741228" CHANGEIDEND="0" TYPEID="8" VALUE="17:18:0105054:309" UPDATEDATE="2025-09-30" STARTDATE="2025-09-30" ENDDATE="2079-06-06" /><PARAM ID="1644782673" OBJECTID="174962647" CHANGEID="689741228" CHANGEIDEND="0" TYPEID="15" VALUE="41" UPDATEDATE="2025-09-30" STARTDATE="2025-09-30" ENDDATE="2079-06-06" /><PARAM ID="1644782674" OBJECTID="174962647" CHANGEID="689741228" CHANGEIDEND="0" TYPEID="13" VALUE="937010000010000008010041000000000" UPDATEDATE="2025-09-30" STARTDATE="2025-09-30" ENDDATE="2079-06-06" /><PARAM ID="1644782675" OBJECTID="174962647" CHANGEID="689741228" CHANGEIDEND="0" TYPEID="21" VALUE="93701000" UPDATEDATE="2025-09-30" STARTDATE="2025-09-30" ENDDATE="2079-06-06" /><PARAM ID="1644783484" OBJECTID="174962736" CHANGEID="689741383" CHANGEIDEND="0" TYPEID="1" VALUE="1700" UPDATEDATE="2025-09-30" STARTDATE="2025-09-30" ENDDATE="2079-06-06" /><PARAM ID="1644783485" OBJECTID="174962736" CHANGEID="689741383" CHANGEIDEND="0" TYPEID="2" VALUE="1700" UPDATEDATE="2025-09-30" STARTDATE="2025-09-30" ENDDATE="2079-06-06" /><PARAM ID="1644783486" OBJECTID="174962736" CHANGEID="689741383" CHANGEIDEND="0" TYPEID="6" VALUE="93401000000" UPDATEDATE="2025-09-30" STARTDATE="2025-09-30" ENDDATE="2079-06-06" /><PARAM ID="1644783487" OBJECTID="174962736" CHANGEID="689741383" CHANGEIDEND="0" TYPEID="7" VALUE="93701000001" UPDATEDATE="2025-09-30" STARTDATE="2025-09-30" ENDDATE="2079-06-06" /><PARAM ID="1644783488" OBJECTID="174962736" CHANGEID="689741383" CHANGEIDEND="0" TYPEID="8" VALUE="17:18:0106003:472" UPDATEDATE="2025-09-30" STARTDATE="2025-09-30" ENDDATE="2079-06-06" /><PARAM ID="1644783489" OBJECTID="174962736" CHANGEID="689741383" CHANGEIDEND="0" TYPEID="15" VALUE="20" UPDATEDATE="2025-09-30" STARTDATE="2025-09-30" ENDDATE="2079-06-06" /><PARAM ID="1644783490" OBJECTID="174962736" CHANGEID="689741383" CHANGEIDEND="0" TYPEID="13" VALUE="937010000010535057410020000000000" UPDATEDATE="2025-09-30" STARTDATE="2025-09-30" ENDDATE="2079-06-06" /><PARAM ID="1644783491" OBJECTID="174962736" CHANGEID="689741383" CHANGEIDEND="0" TYPEID="21" VALUE="93701000" UPDATEDATE="2025-09-30" STARTDATE="2025-09-30" ENDDATE="2079-06-06" /><PARAM ID="1644784081" OBJECTID="174962805" CHANGEID="689741495" CHANGEIDEND="0" TYPEID="1" VALUE="1700" UPDATEDATE="2025-09-30" STARTDATE="2025-09-30" ENDDATE="2079-06-06" /><PARAM ID="1644784082" OBJECTID="174962805" CHANGEID="689741495" CHANGEIDEND="0" TYPEID="2" VALUE="1700" UPDATEDATE="2025-09-30" STARTDATE="2025-09-30" ENDDATE="2079-06-06" /><PARAM ID="1644784083" OBJECTID="174962805" CHANGEID="689741495" CHANGEIDEND="0" TYPEID="6" VALUE="93401000000" UPDATEDATE="2025-09-30" STARTDATE="2025-09-30" ENDDATE="2079-06-06" /><PARAM ID="1644784084" OBJECTID="174962805" CHANGEID="689741495" CHANGEIDEND="0" TYPEID="7" VALUE="93701000001" UPDATEDATE="2025-09-30" STARTDATE="2025-09-30" ENDDATE="2079-06-06" /><PARAM ID="1644784085" OBJECTID="174962805" CHANGEID="689741495" CHANGEIDEND="0" TYPEID="8" VALUE="17:18:0101005:59" UPDATEDATE="2025-09-30" STARTDATE="2025-09-30" ENDDATE="2079-06-06" /><PARAM ID="1644784086" OBJECTID="174962805" CHANGEID="689741495" CHANGEIDEND="0" TYPEID="15" VALUE="12" UPDATEDATE="2025-09-30" STARTDATE="2025-09-30" ENDDATE="2079-06-06" /><PARAM ID="1644784087" OBJECTID="174962805" CHANGEID="689741495" CHANGEIDEND="0" TYPEID="13" VALUE="937010000010540056810012000000000" UPDATEDATE="2025-09-30" STARTDATE="2025-09-30" ENDDATE="2079-06-06" /><PARAM ID="1644784088" OBJECTID="174962805" CHANGEID="689741495" CHANGEIDEND="0" TYPEID="21" VALUE="93701000" UPDATEDATE="2025-09-30" STARTDATE="2025-09-30" ENDDATE="2079-06-06" /><PARAM ID="1644787759" OBJECTID="174963305" CHANGEID="689742274" CHANGEIDEND="0" TYPEID="1" VALUE="1700" UPDATEDATE="2025-09-30" STARTDATE="2025-09-30" ENDDATE="2079-06-06" /><PARAM ID="1644787760" OBJECTID="174963305" CHANGEID="689742274" CHANGEIDEND="0" TYPEID="2" VALUE="1700" UPDATEDATE="2025-09-30" STARTDATE="2025-09-30" ENDDATE="2079-06-06" /><PARAM ID="1644787761" OBJECTID="174963305" CHANGEID="689742274" CHANGEIDEND="0" TYPEID="6" VALUE="93401000000" UPDATEDATE="2025-09-30" STARTDATE="2025-09-30" ENDDATE="2079-06-06" /><PARAM ID="1644787762" OBJECTID="174963305" CHANGEID="689742274" CHANGEIDEND="0" TYPEID="7" VALUE="93701000001" UPDATEDATE="2025-09-30" STARTDATE="2025-09-30" ENDDATE="2079-06-06" /><PARAM ID="1644787763" OBJECTID="174963305" CHANGEID="689742274" CHANGEIDEND="0" TYPEID="8" VALUE="17:18:0104001:3665" UPDATEDATE="2025-09-30" STARTDATE="2025-09-30" ENDDATE="2079-06-06" /><PARAM ID="1644787764" OBJECTID="174963305" CHANGEID="689742274" CHANGEIDEND="0" TYPEID="15" VALUE="6" UPDATEDATE="2025-09-30" STARTDATE="2025-09-30" ENDDATE="2079-06-06" /><PARAM ID="1644787765" OBJECTID="174963305" CHANGEID="689742274" CHANGEIDEND="0" TYPEID="13" VALUE="937010000010836088010006000000000" UPDATEDATE="2025-09-30" STARTDATE="2025-09-30" ENDDATE="2079-06-06" /><PARAM ID="1644787766" OBJECTID="174963305" CHANGEID="689742274" CHANGEIDEND="0" TYPEID="21" VALUE="93701000" UPDATEDATE="2025-09-30" STARTDATE="2025-09-30" ENDDATE="2079-06-06" /></PARAMS>